ziplime/__init__.py
ziplime/__main__.py
ziplime/alembic/README
ziplime/alembic/alembic.ini
ziplime/alembic/env.py
ziplime/alembic/script.py.mako
ziplime/alembic/versions/.keep
ziplime/alembic/versions/498bbf0b3be2_migration.py
ziplime/api.py
ziplime/assets/__init__.py
ziplime/assets/domain/__init__.py
ziplime/assets/domain/asset_type.py
ziplime/assets/domain/continuous_future.py
ziplime/assets/domain/contract_node.py
ziplime/assets/domain/ordered_contracts.py
ziplime/assets/entities/__init__.py
ziplime/assets/entities/asset.py
ziplime/assets/entities/commodity.py
ziplime/assets/entities/currency.py
ziplime/assets/entities/currency_symbol_mapping.py
ziplime/assets/entities/equity.py
ziplime/assets/entities/equity_symbol_mapping.py
ziplime/assets/entities/futures_contract.py
ziplime/assets/entities/symbol_universe.py
ziplime/assets/models/__init__.py
ziplime/assets/models/asset_model.py
ziplime/assets/models/asset_router.py
ziplime/assets/models/commodity_model.py
ziplime/assets/models/currency_model.py
ziplime/assets/models/currency_symbol_mapping_model.py
ziplime/assets/models/dividend.py
ziplime/assets/models/divident_payout.py
ziplime/assets/models/equity_model.py
ziplime/assets/models/equity_supplementary_mapping.py
ziplime/assets/models/equity_symbol_mapping_model.py
ziplime/assets/models/exchange_info.py
ziplime/assets/models/futures_contract_model.py
ziplime/assets/models/futures_root_symbol.py
ziplime/assets/models/merger.py
ziplime/assets/models/split.py
ziplime/assets/models/stock_divident_payout.py
ziplime/assets/models/symbols_universe.py
ziplime/assets/models/symbols_universe_asset.py
ziplime/assets/repositories/__init__.py
ziplime/assets/repositories/adjustments_repository.py
ziplime/assets/repositories/asset_repository.py
ziplime/assets/repositories/sqlalchemy_adjustments_repository.py
ziplime/assets/repositories/sqlalchemy_asset_repository.py
ziplime/assets/services/__init__.py
ziplime/assets/services/asset_service.py
ziplime/assets/utils.py
ziplime-1.13.26.dist-info/METADATA
ziplime-1.13.26.dist-info/WHEEL
ziplime-1.13.26.dist-info/entry_points.txt
ziplime-1.13.26.dist-info/licenses/LICENSE
ziplime-1.13.26.dist-info/RECORD
