Metadata-Version: 2.4
Name: ziplime
Version: 1.13.26
Summary: 
License-File: LICENSE
Author: Ziplime
Requires-Python: >=3.12,<4.0
Classifier: Programming Language :: Python :: 3
Classifier: Programming Language :: Python :: 3.12
Classifier: Programming Language :: Python :: 3.13
Classifier: Programming Language :: Python :: 3.14
Requires-Dist: aiocache (>=0.12.3,<0.13.0)
Requires-Dist: aiofiles (>=24.1.0,<25.0.0)
Requires-Dist: aiosqlite (>=0.21.0,<0.22.0)
Requires-Dist: alembic (>=1.15.2,<2.0.0)
Requires-Dist: asyncclick (>=8.1.8,<9.0.0)
Requires-Dist: empyrical-reloaded (>=0.5.11,<0.6.0)
Requires-Dist: exchange-calendars (>=4.10,<5.0)
Requires-Dist: greenlet (>=3.2.2,<4.0.0)
Requires-Dist: h5py (>=3.13.0,<4.0.0)
Requires-Dist: iso3166 (>=2.1.1,<3.0.0)
Requires-Dist: iso4217 (>=1.12.20240625,<2.0.0)
Requires-Dist: joblib (>=1.5.1,<2.0.0)
Requires-Dist: lime-trader-sdk (>=0.3.9,<0.4.0)
Requires-Dist: limexhub (>=1.10.18,<2.0.0)
Requires-Dist: networkx (>=3.4.2,<4.0.0)
Requires-Dist: numexpr (>=2.10.2,<3.0.0)
Requires-Dist: orjson (>=3.10.15,<4.0.0)
Requires-Dist: pandas (>=2.0.0,<3.0.0)
Requires-Dist: polars (>=1.24.0,<2.0.0)
Requires-Dist: pyarrow (>=19.0.1,<20.0.0)
Requires-Dist: pydantic (>=2.11.2,<3.0.0)
Requires-Dist: pygments (>=2.18.0,<3.0.0)
Requires-Dist: python-dateutil (>=2.9.0.post0,<3.0.0)
Requires-Dist: scipy (>=1.15.3,<2.0.0)
Requires-Dist: setuptools (>=79.0.1,<80.0.0)
Requires-Dist: sqlalchemy (>=2.0.40,<3.0.0)
Requires-Dist: structlog (>=25.4.0,<26.0.0)
Requires-Dist: tabulate (>=0.9.0,<0.10.0)
Requires-Dist: yfinance (>=0.2.65,<0.3.0)
